[
  {
    "speaker": "speaker1",
    "text": "Excuse me . Is this where I catch the bus for the zoo ?",
    "occurrences": [
      "catch"
    ],
    "word_count": 13,
    "stop_word_count": 7,
    "occurrences_count": 1,
    "surprise-NRC-Emotion-Intensity-Lexicon-v1": 0.32,
    "surprise-NRC-Emotion-Intensity-Lexicon-v1_computed": 0.0533,
    "anger": false,
    "fear": false,
    "sadness": false,
    "main_emotion": [
      [
        "surprise",
        "5%"
      ]
    ],
    "combined_emotions": []
  },
  {
    "speaker": "speaker2",
    "text": "Well , you can take the No . 36 bus from here , but then you have to walk about 30 minutes .",
    "occurrences": [],
    "word_count": 20,
    "stop_word_count": 11,
    "occurrences_count": 0,
    "anger": false,
    "fear": false,
    "sadness": false,
    "main_emotion": [],
    "combined_emotions": []
  },
  {
    "speaker": "speaker1",
    "text": "That doesn't sound too bad .",
    "occurrences": [
      "bad"
    ],
    "word_count": 6,
    "stop_word_count": 2,
    "occurrences_count": 1,
    "anger-NRC-Emotion-Intensity-Lexicon-v1": 0.453,
    "anger-NRC-Emotion-Intensity-Lexicon-v1_computed": 0.1133,
    "disgust-NRC-Emotion-Intensity-Lexicon-v1": 0.391,
    "disgust-NRC-Emotion-Intensity-Lexicon-v1_computed": 0.0978,
    "fear-NRC-Emotion-Intensity-Lexicon-v1": 0.375,
    "fear-NRC-Emotion-Intensity-Lexicon-v1_computed": 0.0938,
    "sadness-NRC-Emotion-Intensity-Lexicon-v1": 0.422,
    "sadness-NRC-Emotion-Intensity-Lexicon-v1_computed": 0.1055,
    "anger": true,
    "fear": true,
    "sadness": true,
    "main_emotion": [
      [
        "anger",
        "11%"
      ],
      [
        "sadness",
        "10%"
      ],
      [
        "disgust",
        "9%"
      ]
    ],
    "combined_emotions": []
  },
  {
    "speaker": "speaker2",
    "text": "Actually , if you go to the bus stop in the next block , you can take bus 301 which will let you right off in front of the zoo .",
    "occurrences": [],
    "word_count": 29,
    "stop_word_count": 15,
    "occurrences_count": 0,
    "anger": false,
    "fear": false,
    "sadness": false,
    "main_emotion": [],
    "combined_emotions": []
  },
  {
    "speaker": "speaker1",
    "text": "Maybe that's what I'll do . Thanks a lot .",
    "occurrences": [],
    "word_count": 10,
    "stop_word_count": 4,
    "occurrences_count": 0,
    "anger": false,
    "fear": false,
    "sadness": false,
    "main_emotion": [],
    "combined_emotions": []
  },
  {
    "speaker": "speaker2",
    "text": "You're welcome .",
    "occurrences": [],
    "word_count": 3,
    "stop_word_count": 0,
    "occurrences_count": 0,
    "anger": false,
    "fear": false,
    "sadness": false,
    "main_emotion": [],
    "combined_emotions": []
  }
]