[
  {
    "speaker": "speaker1",
    "text": "Have heard of Paul ?",
    "occurrences": [],
    "word_count": 4,
    "stop_word_count": 2,
    "occurrences_count": 0,
    "anger": false,
    "fear": false,
    "sadness": false,
    "main_emotion": [],
    "combined_emotions": []
  },
  {
    "speaker": "speaker2",
    "text": "No , what ?",
    "occurrences": [],
    "word_count": 3,
    "stop_word_count": 2,
    "occurrences_count": 0,
    "anger": false,
    "fear": false,
    "sadness": false,
    "main_emotion": [],
    "combined_emotions": []
  },
  {
    "speaker": "speaker1",
    "text": "He's got a promotion .",
    "occurrences": [],
    "word_count": 5,
    "stop_word_count": 1,
    "occurrences_count": 0,
    "anger": false,
    "fear": false,
    "sadness": false,
    "main_emotion": [],
    "combined_emotions": []
  },
  {
    "speaker": "speaker2",
    "text": "You're kidding .",
    "occurrences": [],
    "word_count": 3,
    "stop_word_count": 0,
    "occurrences_count": 0,
    "anger": false,
    "fear": false,
    "sadness": false,
    "main_emotion": [],
    "combined_emotions": []
  },
  {
    "speaker": "speaker1",
    "text": "No , they made him vicepresident in charge of sells .",
    "occurrences": [],
    "word_count": 10,
    "stop_word_count": 5,
    "occurrences_count": 0,
    "anger": false,
    "fear": false,
    "sadness": false,
    "main_emotion": [],
    "combined_emotions": []
  },
  {
    "speaker": "speaker2",
    "text": "I don't believe it.He is only being with the company for two years .",
    "occurrences": [],
    "word_count": 14,
    "stop_word_count": 8,
    "occurrences_count": 0,
    "anger": false,
    "fear": false,
    "sadness": false,
    "main_emotion": [],
    "combined_emotions": []
  },
  {
    "speaker": "speaker1",
    "text": "Well , it's true.The board man last thirdly and they choice Paul .",
    "occurrences": [
      "true",
      "board"
    ],
    "word_count": 11,
    "stop_word_count": 3,
    "occurrences_count": 2,
    "anticipation-NRC-Emotion-Intensity-Lexicon-v1": 0.234,
    "anticipation-NRC-Emotion-Intensity-Lexicon-v1_computed": 0.0293,
    "joy-NRC-Emotion-Intensity-Lexicon-v1": 0.328,
    "joy-NRC-Emotion-Intensity-Lexicon-v1_computed": 0.041,
    "trust-NRC-Emotion-Intensity-Lexicon-v1": 0.789,
    "trust-NRC-Emotion-Intensity-Lexicon-v1_computed": 0.0986,
    "anger": false,
    "fear": false,
    "sadness": false,
    "main_emotion": [
      [
        "trust",
        "9%"
      ],
      [
        "joy",
        "4%"
      ],
      [
        "anticipation",
        "2%"
      ]
    ],
    "combined_emotions": []
  },
  {
    "speaker": "speaker2",
    "text": "Well.Good for him .",
    "occurrences": [],
    "word_count": 4,
    "stop_word_count": 2,
    "occurrences_count": 0,
    "anger": false,
    "fear": false,
    "sadness": false,
    "main_emotion": [],
    "combined_emotions": []
  }
]