[
  {
    "speaker": "speaker1",
    "text": "Hello ! Tomorrow I'm going to need a wake-up call .",
    "occurrences": [
      "tomorrow"
    ],
    "word_count": 12,
    "stop_word_count": 4,
    "occurrences_count": 1,
    "anticipation-NRC-Emotion-Intensity-Lexicon-v1": 0.648,
    "anticipation-NRC-Emotion-Intensity-Lexicon-v1_computed": 0.081,
    "anger": false,
    "fear": false,
    "sadness": false,
    "main_emotion": [
      [
        "anticipation",
        "8%"
      ]
    ],
    "combined_emotions": []
  },
  {
    "speaker": "speaker2",
    "text": "Not a problem . What time shall we call you ?",
    "occurrences": [
      "problem",
      "time"
    ],
    "word_count": 11,
    "stop_word_count": 5,
    "occurrences_count": 2,
    "anticipation-NRC-Emotion-Intensity-Lexicon-v1": 0.516,
    "anticipation-NRC-Emotion-Intensity-Lexicon-v1_computed": 0.086,
    "fear-NRC-Emotion-Intensity-Lexicon-v1": 0.266,
    "fear-NRC-Emotion-Intensity-Lexicon-v1_computed": 0.0443,
    "sadness-NRC-Emotion-Intensity-Lexicon-v1": 0.438,
    "sadness-NRC-Emotion-Intensity-Lexicon-v1_computed": 0.073,
    "anger": false,
    "fear": true,
    "sadness": true,
    "main_emotion": [
      [
        "anticipation",
        "8%"
      ],
      [
        "sadness",
        "7%"
      ],
      [
        "fear",
        "4%"
      ]
    ],
    "combined_emotions": []
  },
  {
    "speaker": "speaker1",
    "text": "I always hit the snooze button , so give me two calls , one at 7 and another at 7 fifteen .",
    "occurrences": [
      "hit",
      "calls"
    ],
    "word_count": 20,
    "stop_word_count": 7,
    "occurrences_count": 2,
    "anger-NRC-Emotion-Intensity-Lexicon-v1": 0.667,
    "anger-NRC-Emotion-Intensity-Lexicon-v1_computed": 0.0513,
    "anticipation-NRC-Emotion-Intensity-Lexicon-v1": 0.414,
    "anticipation-NRC-Emotion-Intensity-Lexicon-v1_computed": 0.0318,
    "trust-NRC-Emotion-Intensity-Lexicon-v1": 0.359,
    "trust-NRC-Emotion-Intensity-Lexicon-v1_computed": 0.0276,
    "anger": true,
    "fear": false,
    "sadness": false,
    "main_emotion": [
      [
        "anger",
        "5%"
      ],
      [
        "anticipation",
        "3%"
      ],
      [
        "trust",
        "2%"
      ]
    ],
    "combined_emotions": []
  },
  {
    "speaker": "speaker2",
    "text": "It'll be our pleasure . We'll call you at 7 and then at 7 fifteen .",
    "occurrences": [
      "pleasure"
    ],
    "word_count": 16,
    "stop_word_count": 7,
    "occurrences_count": 1,
    "joy-NRC-Emotion-Intensity-Lexicon-v1": 0.803,
    "joy-NRC-Emotion-Intensity-Lexicon-v1_computed": 0.0892,
    "anger": false,
    "fear": false,
    "sadness": false,
    "main_emotion": [
      [
        "joy",
        "8%"
      ]
    ],
    "combined_emotions": []
  },
  {
    "speaker": "speaker1",
    "text": "Oops , cancel that . Change the second call to 7 thirty will you , please ?",
    "occurrences": [
      "cancel",
      "change"
    ],
    "word_count": 15,
    "stop_word_count": 5,
    "occurrences_count": 2,
    "fear-NRC-Emotion-Intensity-Lexicon-v1": 0.198,
    "fear-NRC-Emotion-Intensity-Lexicon-v1_computed": 0.0198,
    "sadness-NRC-Emotion-Intensity-Lexicon-v1": 0.234,
    "sadness-NRC-Emotion-Intensity-Lexicon-v1_computed": 0.0234,
    "anger": false,
    "fear": true,
    "sadness": true,
    "main_emotion": [
      [
        "sadness",
        "2%"
      ],
      [
        "fear",
        "1%"
      ]
    ],
    "combined_emotions": []
  },
  {
    "speaker": "speaker2",
    "text": "No sooner said than done . Can I help you with anything else ?",
    "occurrences": [
      "help"
    ],
    "word_count": 13,
    "stop_word_count": 5,
    "occurrences_count": 1,
    "fear-NRC-Emotion-Intensity-Lexicon-v1": 0.203,
    "fear-NRC-Emotion-Intensity-Lexicon-v1_computed": 0.0254,
    "anger": false,
    "fear": true,
    "sadness": false,
    "main_emotion": [
      [
        "fear",
        "2%"
      ]
    ],
    "combined_emotions": []
  },
  {
    "speaker": "speaker1",
    "text": "No , that's about it for now . Thanks .",
    "occurrences": [],
    "word_count": 9,
    "stop_word_count": 5,
    "occurrences_count": 0,
    "anger": false,
    "fear": false,
    "sadness": false,
    "main_emotion": [],
    "combined_emotions": []
  },
  {
    "speaker": "speaker2",
    "text": "Okay , sir . Have a pleasant evening .",
    "occurrences": [
      "sir",
      "pleasant"
    ],
    "word_count": 8,
    "stop_word_count": 2,
    "occurrences_count": 2,
    "anticipation-NRC-Emotion-Intensity-Lexicon-v1": 0.523,
    "anticipation-NRC-Emotion-Intensity-Lexicon-v1_computed": 0.0872,
    "joy-NRC-Emotion-Intensity-Lexicon-v1": 0.656,
    "joy-NRC-Emotion-Intensity-Lexicon-v1_computed": 0.1093,
    "surprise-NRC-Emotion-Intensity-Lexicon-v1": 0.242,
    "surprise-NRC-Emotion-Intensity-Lexicon-v1_computed": 0.0403,
    "trust-NRC-Emotion-Intensity-Lexicon-v1": 1.007,
    "trust-NRC-Emotion-Intensity-Lexicon-v1_computed": 0.1678,
    "anger": false,
    "fear": false,
    "sadness": false,
    "main_emotion": [
      [
        "trust",
        "16%"
      ],
      [
        "joy",
        "10%"
      ],
      [
        "anticipation",
        "8%"
      ]
    ],
    "combined_emotions": []
  }
]