[
  {
    "speaker": "speaker1",
    "text": "So Dick , how about getting some coffee for tonight ?"
  },
  {
    "speaker": "speaker2",
    "text": "Coffee ? I don ’ t honestly like that kind of stuff ."
  },
  {
    "speaker": "speaker1",
    "text": "Come on , you can at least try a little , besides your cigarette ."
  },
  {
    "speaker": "speaker2",
    "text": "What ’ s wrong with that ? Cigarette is the thing I go crazy for ."
  },
  {
    "speaker": "speaker1",
    "text": "Not for me , Dick ."
  }
]