[
  {
    "speaker": "speaker1",
    "text": "Room service ."
  },
  {
    "speaker": "speaker2",
    "text": "Good morning . This is room 113 . I'd like some breakfast , please ."
  },
  {
    "speaker": "speaker1",
    "text": "Right . Excuse me . Mrs . Jones ?"
  },
  {
    "speaker": "speaker2",
    "text": "That's right ."
  },
  {
    "speaker": "speaker1",
    "text": "What can I do for you ?"
  },
  {
    "speaker": "speaker2",
    "text": "I'd like some grapefruit juice , marmalade , two scrambled eggs with two sausages , toast , and a pot of black coffee , please . How long will it take ?"
  },
  {
    "speaker": "speaker1",
    "text": "Just a few minutes , ma'am ."
  },
  {
    "speaker": "speaker2",
    "text": "Great . Thank you ."
  }
]