[
  {
    "speaker": "speaker1",
    "text": "What are the most popular sports in your country ?",
    "occurrences": [
      "popular"
    ],
    "word_count": 10,
    "stop_word_count": 6,
    "occurrences_count": 1,
    "trust-NRC-Emotion-Intensity-Lexicon-v1": 0.398,
    "trust-NRC-Emotion-Intensity-Lexicon-v1_computed": 0.0995,
    "anger": false,
    "fear": false,
    "sadness": false,
    "main_emotion": [
      [
        "trust",
        "9%"
      ]
    ],
    "combined_emotions": []
  },
  {
    "speaker": "speaker2",
    "text": "Swimming in summer and skating in winter.What ' s your favorite sport ?",
    "occurrences": [
      "summer",
      "favorite"
    ],
    "word_count": 13,
    "stop_word_count": 5,
    "occurrences_count": 2,
    "joy-NRC-Emotion-Intensity-Lexicon-v1": 1.279,
    "joy-NRC-Emotion-Intensity-Lexicon-v1_computed": 0.1599,
    "trust-NRC-Emotion-Intensity-Lexicon-v1": 0.484,
    "trust-NRC-Emotion-Intensity-Lexicon-v1_computed": 0.0605,
    "anger": false,
    "fear": false,
    "sadness": false,
    "main_emotion": [
      [
        "joy",
        "15%"
      ],
      [
        "trust",
        "6%"
      ]
    ],
    "combined_emotions": []
  },
  {
    "speaker": "speaker1",
    "text": "Jogging and bowling . Do you know how to practise Bungfu ?",
    "occurrences": [
      "practise"
    ],
    "word_count": 11,
    "stop_word_count": 5,
    "occurrences_count": 1,
    "anticipation-NRC-Emotion-Intensity-Lexicon-v1": 0.508,
    "anticipation-NRC-Emotion-Intensity-Lexicon-v1_computed": 0.0847,
    "anger": false,
    "fear": false,
    "sadness": false,
    "main_emotion": [
      [
        "anticipation",
        "8%"
      ]
    ],
    "combined_emotions": []
  },
  {
    "speaker": "speaker2",
    "text": "No I don't But l do Taijiquan or Shadow boxing.People everywhere in China usually do Taijiquan early in the morning.It can help people keep fit.It has a history of over three hundred years .",
    "occurrences": [
      "boxing",
      "morning",
      "help",
      "fit"
    ],
    "word_count": 28,
    "stop_word_count": 12,
    "occurrences_count": 4,
    "anger-NRC-Emotion-Intensity-Lexicon-v1": 0.394,
    "anger-NRC-Emotion-Intensity-Lexicon-v1_computed": 0.0246,
    "fear-NRC-Emotion-Intensity-Lexicon-v1": 0.203,
    "fear-NRC-Emotion-Intensity-Lexicon-v1_computed": 0.0127,
    "joy-NRC-Emotion-Intensity-Lexicon-v1": 0.5,
    "joy-NRC-Emotion-Intensity-Lexicon-v1_computed": 0.0312,
    "anger": true,
    "fear": true,
    "sadness": false,
    "main_emotion": [
      [
        "joy",
        "3%"
      ],
      [
        "anger",
        "2%"
      ],
      [
        "fear",
        "1%"
      ]
    ],
    "combined_emotions": []
  },
  {
    "speaker": "speaker1",
    "text": "Is it easy to learn ?",
    "occurrences": [],
    "word_count": 6,
    "stop_word_count": 3,
    "occurrences_count": 0,
    "anger": false,
    "fear": false,
    "sadness": false,
    "main_emotion": [],
    "combined_emotions": []
  },
  {
    "speaker": "speaker2",
    "text": "Yes . it is I can teach you if you like .",
    "occurrences": [
      "teach",
      "like"
    ],
    "word_count": 11,
    "stop_word_count": 6,
    "occurrences_count": 2,
    "joy-NRC-Emotion-Intensity-Lexicon-v1": 0.212,
    "joy-NRC-Emotion-Intensity-Lexicon-v1_computed": 0.0424,
    "surprise-NRC-Emotion-Intensity-Lexicon-v1": 0.125,
    "surprise-NRC-Emotion-Intensity-Lexicon-v1_computed": 0.025,
    "trust-NRC-Emotion-Intensity-Lexicon-v1": 1.101,
    "trust-NRC-Emotion-Intensity-Lexicon-v1_computed": 0.2202,
    "anger": false,
    "fear": false,
    "sadness": false,
    "main_emotion": [
      [
        "trust",
        "22%"
      ],
      [
        "joy",
        "4%"
      ],
      [
        "surprise",
        "2%"
      ]
    ],
    "combined_emotions": []
  },
  {
    "speaker": "speaker1",
    "text": "Thank you . I can teach you how to bowl .",
    "occurrences": [
      "teach"
    ],
    "word_count": 11,
    "stop_word_count": 6,
    "occurrences_count": 1,
    "joy-NRC-Emotion-Intensity-Lexicon-v1": 0.212,
    "joy-NRC-Emotion-Intensity-Lexicon-v1_computed": 0.0424,
    "surprise-NRC-Emotion-Intensity-Lexicon-v1": 0.125,
    "surprise-NRC-Emotion-Intensity-Lexicon-v1_computed": 0.025,
    "trust-NRC-Emotion-Intensity-Lexicon-v1": 0.617,
    "trust-NRC-Emotion-Intensity-Lexicon-v1_computed": 0.1234,
    "anger": false,
    "fear": false,
    "sadness": false,
    "main_emotion": [
      [
        "trust",
        "12%"
      ],
      [
        "joy",
        "4%"
      ],
      [
        "surprise",
        "2%"
      ]
    ],
    "combined_emotions": []
  },
  {
    "speaker": "speaker2",
    "text": "Right . Let's help each other .",
    "occurrences": [
      "help"
    ],
    "word_count": 7,
    "stop_word_count": 2,
    "occurrences_count": 1,
    "fear-NRC-Emotion-Intensity-Lexicon-v1": 0.203,
    "fear-NRC-Emotion-Intensity-Lexicon-v1_computed": 0.0406,
    "anger": false,
    "fear": true,
    "sadness": false,
    "main_emotion": [
      [
        "fear",
        "4%"
      ]
    ],
    "combined_emotions": []
  }
]